vietnamese_address_parser/__init__.py
vietnamese_address_parser/cli.py
vietnamese_address_parser/main.py
vietnamese_address_parser/tinh_qh_px_20_05_2025.json
vietnamese_address_parser-0.1.10.dist-info/METADATA
vietnamese_address_parser-0.1.10.dist-info/WHEEL
vietnamese_address_parser-0.1.10.dist-info/entry_points.txt
vietnamese_address_parser-0.1.10.dist-info/top_level.txt
vietnamese_address_parser-0.1.10.dist-info/RECORD
