Metadata-Version: 2.4
Name: vietnamese_address_parser
Version: 0.1.10
Author: Dang Anh Dat
Author-email: contact.anhdat@gmail.com
Requires-Python: >=3.9
Requires-Dist: requests
Dynamic: author
Dynamic: author-email
Dynamic: description
Dynamic: description-content-type
Dynamic: requires-dist
Dynamic: requires-python
